ecowitt_wn90lp/__init__.py
ecowitt_wn90lp/__main__.py
ecowitt_wn90lp/py.typed
ecowitt_wn90lp/reset.py
ecowitt_wn90lp/ws90.py
ecowitt_wn90lp-1.2.0.dist-info/LICENSE
ecowitt_wn90lp-1.2.0.dist-info/METADATA
ecowitt_wn90lp-1.2.0.dist-info/WHEEL
ecowitt_wn90lp-1.2.0.dist-info/RECORD
