Metadata-Version: 2.3
Name: ecowitt-wn90lp
Version: 1.2.0
Summary: Ecowitt WN90LP (WS90 RS485 Modbus) client
License: BSD-2-Clause
Author: Corey Matyas
Author-email: corey@hextronics.com
Requires-Python: >=3.9
Classifier: License :: OSI Approved :: BSD License
Classifier: Framework :: AsyncIO
Classifier: Operating System :: OS Independent
Classifier: Programming Language :: Python :: 3
Requires-Dist: pymodbus[serial] (>=3.6.9,<3.9.0)
Project-URL: Homepage, https://github.com/HexMiami/ecowitt-wn90lp
